<?xml version="1.0" encoding="UTF-8" ?>
<!DOCTYPE Entity SYSTEM "jbo_03_01.dtd">
<!---->
<Entity
  xmlns="http://xmlns.oracle.com/bc4j"
  Name="StoreEO"
  Version="12.2.1.9.14"
  InheritPersonalization="merge"
  DBObjectType="table"
  DBObjectName="POS_STORES"
  AliasName="StoreEO"
  BindingStyle="OracleName">
  <Attribute
    Name="StoreId"
    ColumnName="STORE_ID"
    SQLType="NUMERIC"
    Type="oracle.jbo.domain.DBSequence"
    ColumnType="NUMBER"
    TableName="POS_STORES"
    PrimaryKey="true"
    IsUpdateable="while_insert"
    DefaultValue="@0"
    Domain="oracle.jbo.domain.DBSequence"
    RetrievedOnInsert="true">
    <Properties>
      <SchemaBasedProperties>
        <LABEL
          ResId="demasylabs.oracle.apps.fusion.pos.model.adfbc.entities.StoreEO.StoreId_LABEL"/>
      </SchemaBasedProperties>
    </Properties>
  </Attribute>
  <Attribute
    Name="CountryCode"
    IsNotNull="true"
    Precision="3"
    ColumnName="COUNTRY_CODE"
    SQLType="VARCHAR"
    Type="java.lang.String"
    ColumnType="VARCHAR2"
    TableName="POS_STORES"
    IsUpdateable="while_insert">
    <DesignTime>
      <Attr Name="_DisplaySize" Value="3"/>
    </DesignTime>
    <Properties>
      <SchemaBasedProperties>
        <LABEL
          ResId="demasylabs.oracle.apps.fusion.pos.model.adfbc.entities.StoreEO.CountryCode_LABEL"/>
      </SchemaBasedProperties>
    </Properties>
  </Attribute>
  <Attribute
    Name="ShortName"
    IsUnique="true"
    IsNotNull="true"
    Precision="50"
    ColumnName="SHORT_NAME"
    SQLType="VARCHAR"
    Type="java.lang.String"
    ColumnType="VARCHAR2"
    TableName="POS_STORES"
    IsUpdateable="while_insert">
    <DesignTime>
      <Attr Name="_DisplaySize" Value="50"/>
    </DesignTime>
    <Properties>
      <SchemaBasedProperties>
        <LABEL
          ResId="demasylabs.oracle.apps.fusion.pos.model.adfbc.entities.StoreEO.ShortName_LABEL"/>
      </SchemaBasedProperties>
    </Properties>
  </Attribute>
  <Attribute
    Name="Name"
    IsUnique="true"
    IsNotNull="true"
    Precision="100"
    ColumnName="NAME"
    SQLType="VARCHAR"
    Type="java.lang.String"
    ColumnType="VARCHAR2"
    TableName="POS_STORES">
    <DesignTime>
      <Attr Name="_DisplaySize" Value="100"/>
    </DesignTime>
    <Properties>
      <SchemaBasedProperties>
        <LABEL
          ResId="demasylabs.oracle.apps.fusion.pos.model.adfbc.entities.StoreEO.Name_LABEL"/>
      </SchemaBasedProperties>
    </Properties>
  </Attribute>
  <Attribute
    Name="Description"
    Precision="4000"
    ColumnName="DESCRIPTION"
    SQLType="VARCHAR"
    Type="java.lang.String"
    ColumnType="VARCHAR2"
    TableName="POS_STORES">
    <DesignTime>
      <Attr Name="_DisplaySize" Value="4000"/>
    </DesignTime>
    <Properties>
      <SchemaBasedProperties>
        <LABEL
          ResId="demasylabs.oracle.apps.fusion.pos.model.adfbc.entities.StoreEO.Description_LABEL"/>
      </SchemaBasedProperties>
    </Properties>
  </Attribute>
  <Attribute
    Name="StartDate"
    IsNotNull="true"
    ColumnName="START_DATE"
    SQLType="DATE"
    Type="java.sql.Timestamp"
    ColumnType="DATE"
    TableName="POS_STORES">
    <TransientExpression
      Name="ExpressionScript"
      trustMode="untrusted"
      CodeSourceName="StoreEORow"/>
    <Properties>
      <SchemaBasedProperties>
        <LABEL
          ResId="demasylabs.oracle.apps.fusion.pos.model.adfbc.entities.StoreEO.StartDate_LABEL"/>
      </SchemaBasedProperties>
    </Properties>
  </Attribute>
  <Attribute
    Name="EndDate"
    ColumnName="END_DATE"
    SQLType="DATE"
    Type="java.sql.Timestamp"
    ColumnType="DATE"
    TableName="POS_STORES">
    <Properties>
      <SchemaBasedProperties>
        <LABEL
          ResId="demasylabs.oracle.apps.fusion.pos.model.adfbc.entities.StoreEO.EndDate_LABEL"/>
      </SchemaBasedProperties>
    </Properties>
  </Attribute>
  <Attribute
    Name="EnabledFlag"
    IsNotNull="true"
    Precision="1"
    ColumnName="ENABLED_FLAG"
    SQLType="VARCHAR"
    Type="java.lang.String"
    ColumnType="VARCHAR2"
    TableName="POS_STORES">
    <DesignTime>
      <Attr Name="_DisplaySize" Value="1"/>
    </DesignTime>
    <Properties>
      <SchemaBasedProperties>
        <LABEL
          ResId="demasylabs.oracle.apps.fusion.pos.model.adfbc.entities.StoreEO.EnabledFlag_LABEL"/>
        <DISPLAYWIDTH
          Value="5"/>
      </SchemaBasedProperties>
    </Properties>
  </Attribute>
  <Attribute
    Name="CreatedBy"
    IsNotNull="true"
    ColumnName="CREATED_BY"
    SQLType="NUMERIC"
    Type="java.math.BigDecimal"
    ColumnType="NUMBER"
    TableName="POS_STORES">
    <Properties>
      <SchemaBasedProperties>
        <LABEL
          ResId="demasylabs.oracle.apps.fusion.pos.model.adfbc.entities.StoreEO.CreatedBy_LABEL"/>
      </SchemaBasedProperties>
    </Properties>
  </Attribute>
  <Attribute
    Name="CreationDate"
    IsNotNull="true"
    ColumnName="CREATION_DATE"
    SQLType="DATE"
    Type="java.sql.Timestamp"
    ColumnType="DATE"
    TableName="POS_STORES"
    IsUpdateable="while_insert"
    HistoryColumn="DateHistory">
    <Properties>
      <SchemaBasedProperties>
        <LABEL
          ResId="demasylabs.oracle.apps.fusion.pos.model.adfbc.entities.StoreEO.CreationDate_LABEL"/>
      </SchemaBasedProperties>
    </Properties>
  </Attribute>
  <Attribute
    Name="LastUpdatedBy"
    IsNotNull="true"
    ColumnName="LAST_UPDATED_BY"
    SQLType="NUMERIC"
    Type="java.math.BigDecimal"
    ColumnType="NUMBER"
    TableName="POS_STORES">
    <Properties>
      <SchemaBasedProperties>
        <LABEL
          ResId="demasylabs.oracle.apps.fusion.pos.model.adfbc.entities.StoreEO.LastUpdatedBy_LABEL"/>
      </SchemaBasedProperties>
    </Properties>
  </Attribute>
  <Attribute
    Name="LastUpdateDate"
    IsNotNull="true"
    ColumnName="LAST_UPDATE_DATE"
    SQLType="DATE"
    Type="java.sql.Timestamp"
    ColumnType="DATE"
    TableName="POS_STORES"
    HistoryColumn="DateHistory">
    <Properties>
      <SchemaBasedProperties>
        <LABEL
          ResId="demasylabs.oracle.apps.fusion.pos.model.adfbc.entities.StoreEO.LastUpdateDate_LABEL"/>
      </SchemaBasedProperties>
    </Properties>
  </Attribute>
  <Attribute
    Name="ObjectVersionId"
    IsNotNull="true"
    ColumnName="OBJECT_VERSION_ID"
    SQLType="NUMERIC"
    Type="java.math.BigDecimal"
    ColumnType="NUMBER"
    TableName="POS_STORES"
    HistoryColumn="VersionHistory">
    <Properties>
      <SchemaBasedProperties>
        <LABEL
          ResId="demasylabs.oracle.apps.fusion.pos.model.adfbc.entities.StoreEO.ObjectVersionId_LABEL"/>
      </SchemaBasedProperties>
    </Properties>
  </Attribute>
  <AccessorAttribute
    Name="StoreBranch"
    Association="demasylabs.oracle.apps.fusion.pos.model.adfbc.entities.associations.PsbStoreIdFkAssoc"
    AssociationEnd="demasylabs.oracle.apps.fusion.pos.model.adfbc.entities.associations.PsbStoreIdFkAssoc.StoreBranch"
    AssociationOtherEnd="demasylabs.oracle.apps.fusion.pos.model.adfbc.entities.associations.PsbStoreIdFkAssoc.Store"
    Type="oracle.jbo.RowIterator"
    IsUpdateable="false"/>
  <Key
    Name="PsNameUn">
    <DesignTime>
      <Attr Name="_isUnique" Value="true"/>
      <Attr Name="_DBObjectName" Value="PS_NAME_UN"/>
    </DesignTime>
    <AttrArray Name="Attributes">
      <Item Value="demasylabs.oracle.apps.fusion.pos.model.adfbc.entities.StoreEO.Name"/>
    </AttrArray>
  </Key>
  <Key
    Name="PsShortNameUn">
    <DesignTime>
      <Attr Name="_isUnique" Value="true"/>
      <Attr Name="_DBObjectName" Value="PS_SHORT_NAME_UN"/>
    </DesignTime>
    <AttrArray Name="Attributes">
      <Item Value="demasylabs.oracle.apps.fusion.pos.model.adfbc.entities.StoreEO.ShortName"/>
    </AttrArray>
  </Key>
  <Key
    Name="PsStoreIdPk"
    PrimaryKey="true">
    <DesignTime>
      <Attr Name="_DBObjectName" Value="PS_STORE_ID_PK"/>
    </DesignTime>
    <AttrArray Name="Attributes">
      <Item Value="demasylabs.oracle.apps.fusion.pos.model.adfbc.entities.StoreEO.StoreId"/>
    </AttrArray>
  </Key>
  <ResourceBundle>
    <PropertiesBundle
      PropertiesFile="demasylabs.oracle.apps.fusion.pos.model.ModelBundle"/>
  </ResourceBundle>
</Entity>
